{
  "abstract": true,
  "anchor": "",
  "category": "classes",
  "const": false,
  "definition": "",
  "explicit": false,
  "fullname": "batt::detail::AbstractMoveFn",
  "hasAdditionalMembers": false,
  "hasDetails": true,
  "inline": false,
  "kind": "class",
  "language": "cpp",
  "location": {
    "bodyEnd": 98,
    "bodyFile": "batteries/small_fn.hpp",
    "bodyStart": 81,
    "column": 1,
    "file": "batteries/small_fn.hpp",
    "line": 80
  },
  "name": "batt::detail::AbstractMoveFn",
  "override": false,
  "parent": {
    "anchor": "",
    "category": "namespaces",
    "fullname": "batt::detail",
    "kind": "namespace",
    "language": "cpp",
    "name": "batt::detail",
    "refid": "namespacebatt_1_1detail",
    "title": "batt::detail",
    "url": "/_autogen/Namespaces/namespacebatt_1_1detail/",
    "visibility": "public"
  },
  "parentBreadcrumbs": [
    {
      "anchor": "",
      "category": "namespaces",
      "fullname": "batt",
      "kind": "namespace",
      "language": "cpp",
      "name": "batt",
      "refid": "namespacebatt",
      "title": "batt",
      "url": "/_autogen/Namespaces/namespacebatt/",
      "visibility": "public"
    },
    {
      "anchor": "",
      "category": "namespaces",
      "fullname": "batt::detail",
      "kind": "namespace",
      "language": "cpp",
      "name": "batt::detail",
      "refid": "namespacebatt_1_1detail",
      "title": "batt::detail",
      "url": "/_autogen/Namespaces/namespacebatt_1_1detail/",
      "visibility": "public"
    }
  ],
  "protectedFunctions": [
    {
      "abstract": false,
      "anchor": "#function-abstractmovefn",
      "argsString": "()=default",
      "category": "functions",
      "const": false,
      "default": true,
      "definition": "batt::detail::AbstractMoveFn< kMoveOnly, Result, Args >::AbstractMoveFn",
      "deleted": false,
      "explicit": false,
      "fullname": "batt::detail::AbstractMoveFn::AbstractMoveFn",
      "hasDetails": false,
      "inline": false,
      "kind": "function",
      "language": "cpp",
      "location": {
        "column": 5,
        "file": "batteries/small_fn.hpp",
        "line": 83
      },
      "name": "AbstractMoveFn",
      "override": false,
      "params": [],
      "pureVirtual": false,
      "refid": "classbatt_1_1detail_1_1AbstractMoveFn_1a7c597f692a0925d074a06035b48ee8bd",
      "static": false,
      "strong": false,
      "title": "AbstractMoveFn",
      "url": "/_autogen/Classes/classbatt_1_1detail_1_1AbstractMoveFn/#function-abstractmovefn",
      "virtual": false,
      "visibility": "protected"
    }
  ],
  "publicFunctions": [
    {
      "abstract": false,
      "anchor": "#function-abstractmovefn",
      "argsString": "(const AbstractMoveFn &)=delete",
      "category": "functions",
      "const": false,
      "default": false,
      "definition": "batt::detail::AbstractMoveFn< kMoveOnly, Result, Args >::AbstractMoveFn",
      "deleted": true,
      "explicit": false,
      "fullname": "batt::detail::AbstractMoveFn::AbstractMoveFn",
      "hasDetails": false,
      "inline": false,
      "kind": "function",
      "language": "cpp",
      "location": {
        "column": 5,
        "file": "batteries/small_fn.hpp",
        "line": 86
      },
      "name": "AbstractMoveFn",
      "override": false,
      "params": [
        {
          "name": "",
          "type": "const [AbstractMoveFn](/_autogen/Classes/classbatt_1_1detail_1_1AbstractMoveFn/) &",
          "typePlain": "const AbstractMoveFn &"
        }
      ],
      "pureVirtual": false,
      "refid": "classbatt_1_1detail_1_1AbstractMoveFn_1af85885f17763051decb013389dcb966f",
      "static": false,
      "strong": false,
      "title": "AbstractMoveFn",
      "url": "/_autogen/Classes/classbatt_1_1detail_1_1AbstractMoveFn/#function-abstractmovefn",
      "virtual": false,
      "visibility": "public"
    },
    {
      "abstract": false,
      "anchor": "#function-operator=",
      "argsString": "(const AbstractMoveFn &)=delete",
      "category": "functions",
      "const": false,
      "default": false,
      "definition": "AbstractMoveFn& batt::detail::AbstractMoveFn< kMoveOnly, Result, Args >::operator=",
      "deleted": true,
      "explicit": false,
      "fullname": "batt::detail::AbstractMoveFn::operator=",
      "hasDetails": false,
      "inline": false,
      "kind": "function",
      "language": "cpp",
      "location": {
        "column": 20,
        "file": "batteries/small_fn.hpp",
        "line": 87
      },
      "name": "operator=",
      "override": false,
      "params": [
        {
          "name": "",
          "type": "const [AbstractMoveFn](/_autogen/Classes/classbatt_1_1detail_1_1AbstractMoveFn/) &",
          "typePlain": "const AbstractMoveFn &"
        }
      ],
      "pureVirtual": false,
      "refid": "classbatt_1_1detail_1_1AbstractMoveFn_1a76d9464eca11bae567bf6ac238fd9286",
      "static": false,
      "strong": false,
      "title": "operator=",
      "type": "[AbstractMoveFn](/_autogen/Classes/classbatt_1_1detail_1_1AbstractMoveFn/) &",
      "typePlain": "AbstractMoveFn &",
      "url": "/_autogen/Classes/classbatt_1_1detail_1_1AbstractMoveFn/#function-operator=",
      "virtual": false,
      "visibility": "public"
    },
    {
      "abstract": false,
      "anchor": "#function-~abstractmovefn",
      "argsString": "()=default",
      "category": "functions",
      "const": false,
      "default": true,
      "definition": "virtual batt::detail::AbstractMoveFn< kMoveOnly, Result, Args >::~AbstractMoveFn",
      "deleted": false,
      "explicit": false,
      "fullname": "batt::detail::AbstractMoveFn::~AbstractMoveFn",
      "hasDetails": false,
      "inline": false,
      "kind": "function",
      "language": "cpp",
      "location": {
        "column": 13,
        "file": "batteries/small_fn.hpp",
        "line": 89
      },
      "name": "~AbstractMoveFn",
      "override": false,
      "params": [],
      "pureVirtual": false,
      "refid": "classbatt_1_1detail_1_1AbstractMoveFn_1a10cbe47ce21d108c67d7b62b1a56dd77",
      "static": false,
      "strong": false,
      "title": "~AbstractMoveFn",
      "url": "/_autogen/Classes/classbatt_1_1detail_1_1AbstractMoveFn/#function-~abstractmovefn",
      "virtual": true,
      "visibility": "public"
    },
    {
      "abstract": false,
      "anchor": "#function-invoke",
      "argsString": "(Args... args) noexcept -> Result=0",
      "category": "functions",
      "const": false,
      "default": false,
      "definition": "virtual auto batt::detail::AbstractMoveFn< kMoveOnly, Result, Args >::invoke",
      "deleted": false,
      "explicit": false,
      "fullname": "batt::detail::AbstractMoveFn::invoke",
      "hasDetails": false,
      "inline": false,
      "kind": "function",
      "language": "cpp",
      "location": {
        "column": 18,
        "file": "batteries/small_fn.hpp",
        "line": 91
      },
      "name": "invoke",
      "override": false,
      "params": [
        {
          "name": "args",
          "type": "Args...",
          "typePlain": "Args..."
        }
      ],
      "pureVirtual": true,
      "refid": "classbatt_1_1detail_1_1AbstractMoveFn_1ab77aac5707bb8f5e8fe146a6bd9efbc1",
      "static": false,
      "strong": false,
      "title": "invoke",
      "type": "auto",
      "typePlain": "auto",
      "url": "/_autogen/Classes/classbatt_1_1detail_1_1AbstractMoveFn/#function-invoke",
      "virtual": true,
      "visibility": "public"
    },
    {
      "abstract": false,
      "anchor": "#function-move",
      "argsString": "(void *storage, usize size) noexcept -> AbstractFn< kMoveOnly, Result, Args... > *=0",
      "category": "functions",
      "const": false,
      "default": false,
      "definition": "virtual auto batt::detail::AbstractMoveFn< kMoveOnly, Result, Args >::move",
      "deleted": false,
      "explicit": false,
      "fullname": "batt::detail::AbstractMoveFn::move",
      "hasDetails": false,
      "inline": false,
      "kind": "function",
      "language": "cpp",
      "location": {
        "column": 18,
        "file": "batteries/small_fn.hpp",
        "line": 97
      },
      "name": "move",
      "override": false,
      "params": [
        {
          "name": "storage",
          "type": "void *",
          "typePlain": "void *"
        },
        {
          "name": "size",
          "type": "usize",
          "typePlain": "usize"
        }
      ],
      "pureVirtual": true,
      "refid": "classbatt_1_1detail_1_1AbstractMoveFn_1ab21b3773e55118e45396b366e07eece2",
      "static": false,
      "strong": false,
      "title": "move",
      "type": "auto",
      "typePlain": "auto",
      "url": "/_autogen/Classes/classbatt_1_1detail_1_1AbstractMoveFn/#function-move",
      "virtual": true,
      "visibility": "public"
    }
  ],
  "refid": "classbatt_1_1detail_1_1AbstractMoveFn",
  "static": false,
  "strong": false,
  "templateParams": [
    {
      "name": "kMoveOnly",
      "type": "bool",
      "typePlain": "bool"
    },
    {
      "name": "",
      "type": "typename Result",
      "typePlain": "typename Result"
    },
    {
      "name": "Args",
      "type": "typename...",
      "typePlain": "typename..."
    }
  ],
  "title": "batt::detail::AbstractMoveFn",
  "url": "/_autogen/Classes/classbatt_1_1detail_1_1AbstractMoveFn/",
  "visibility": "public"
}