{
  "abstract": false,
  "anchor": "",
  "baseClasses": [
    {
      "external": true,
      "name": "batt::RefCounted< ManagedBuffer >",
      "refid": null,
      "virtual": "non-virtual",
      "visibility": "public"
    }
  ],
  "category": "classes",
  "const": false,
  "definition": "",
  "explicit": false,
  "fullname": "batt::ManagedBuffer",
  "hasAdditionalMembers": false,
  "hasDetails": false,
  "inline": false,
  "kind": "class",
  "language": "cpp",
  "location": {
    "bodyEnd": 191,
    "bodyFile": "batteries/buffer.hpp",
    "bodyStart": 170,
    "column": 1,
    "file": "batteries/buffer.hpp",
    "line": 169
  },
  "name": "batt::ManagedBuffer",
  "override": false,
  "parent": {
    "anchor": "",
    "category": "namespaces",
    "fullname": "batt",
    "kind": "namespace",
    "language": "cpp",
    "name": "batt",
    "refid": "namespacebatt",
    "title": "batt",
    "url": "/_autogen/Namespaces/namespacebatt/",
    "visibility": "public"
  },
  "parentBreadcrumbs": [
    {
      "anchor": "",
      "category": "namespaces",
      "fullname": "batt",
      "kind": "namespace",
      "language": "cpp",
      "name": "batt",
      "refid": "namespacebatt",
      "title": "batt",
      "url": "/_autogen/Namespaces/namespacebatt/",
      "visibility": "public"
    }
  ],
  "privateAttributes": [
    {
      "abstract": false,
      "anchor": "#variable-storage-",
      "category": "attributes",
      "const": false,
      "definition": "std::array<char, ManagedBuffer::kCapacity> batt::ManagedBuffer::storage_",
      "explicit": false,
      "fullname": "batt::ManagedBuffer::storage_",
      "hasDetails": false,
      "inline": false,
      "kind": "variable",
      "language": "cpp",
      "location": {
        "bodyFile": "batteries/buffer.hpp",
        "bodyStart": 190,
        "column": 16,
        "file": "batteries/buffer.hpp",
        "line": 190
      },
      "name": "storage_",
      "override": false,
      "refid": "classbatt_1_1ManagedBuffer_1a39cd4da50ca7080b5ab7860823855925",
      "static": false,
      "strong": false,
      "title": "storage_",
      "type": "std::array< char, ManagedBuffer::kCapacity >",
      "typePlain": "std::array< char, ManagedBuffer::kCapacity >",
      "url": "/_autogen/Classes/classbatt_1_1ManagedBuffer/#variable-storage-",
      "visibility": "private"
    }
  ],
  "publicAttributes": [
    {
      "abstract": false,
      "anchor": "#variable-kcapacity",
      "category": "attributes",
      "const": false,
      "definition": "constexpr usize batt::ManagedBuffer::kCapacity",
      "explicit": false,
      "fullname": "batt::ManagedBuffer::kCapacity",
      "hasDetails": false,
      "initializer": "= 4096",
      "inline": false,
      "kind": "variable",
      "language": "cpp",
      "location": {
        "bodyFile": "batteries/buffer.hpp",
        "bodyStart": 172,
        "column": 28,
        "file": "batteries/buffer.hpp",
        "line": 172
      },
      "name": "kCapacity",
      "override": false,
      "refid": "classbatt_1_1ManagedBuffer_1ab894ee422ad6f7b22730aeda8a4f81e3",
      "static": true,
      "strong": false,
      "title": "kCapacity",
      "type": "constexpr usize",
      "typePlain": "constexpr usize",
      "url": "/_autogen/Classes/classbatt_1_1ManagedBuffer/#variable-kcapacity",
      "visibility": "public"
    }
  ],
  "publicFunctions": [
    {
      "abstract": false,
      "anchor": "#function-data",
      "argsString": "()",
      "category": "functions",
      "const": false,
      "default": false,
      "definition": "char* batt::ManagedBuffer::data",
      "deleted": false,
      "explicit": false,
      "fullname": "batt::ManagedBuffer::data",
      "hasDetails": false,
      "inline": true,
      "kind": "function",
      "language": "cpp",
      "location": {
        "bodyEnd": 177,
        "bodyFile": "batteries/buffer.hpp",
        "bodyStart": 174,
        "column": 10,
        "file": "batteries/buffer.hpp",
        "line": 174
      },
      "name": "data",
      "override": false,
      "params": [],
      "pureVirtual": false,
      "refid": "classbatt_1_1ManagedBuffer_1adbef7d5f254b75a3305dac573b9105fa",
      "static": false,
      "strong": false,
      "title": "data",
      "type": "char *",
      "typePlain": "char *",
      "url": "/_autogen/Classes/classbatt_1_1ManagedBuffer/#function-data",
      "virtual": false,
      "visibility": "public"
    },
    {
      "abstract": false,
      "anchor": "#function-data",
      "argsString": "() const",
      "category": "functions",
      "const": true,
      "default": false,
      "definition": "const char* batt::ManagedBuffer::data",
      "deleted": false,
      "explicit": false,
      "fullname": "batt::ManagedBuffer::data",
      "hasDetails": false,
      "inline": true,
      "kind": "function",
      "language": "cpp",
      "location": {
        "bodyEnd": 182,
        "bodyFile": "batteries/buffer.hpp",
        "bodyStart": 179,
        "column": 16,
        "file": "batteries/buffer.hpp",
        "line": 179
      },
      "name": "data",
      "override": false,
      "params": [],
      "pureVirtual": false,
      "refid": "classbatt_1_1ManagedBuffer_1ac1e6d6fb81a45148b5a9a20c00f56a10",
      "static": false,
      "strong": false,
      "title": "data",
      "type": "const char *",
      "typePlain": "const char *",
      "url": "/_autogen/Classes/classbatt_1_1ManagedBuffer/#function-data",
      "virtual": false,
      "visibility": "public"
    },
    {
      "abstract": false,
      "anchor": "#function-size",
      "argsString": "() const",
      "category": "functions",
      "const": true,
      "default": false,
      "definition": "usize batt::ManagedBuffer::size",
      "deleted": false,
      "explicit": false,
      "fullname": "batt::ManagedBuffer::size",
      "hasDetails": false,
      "inline": true,
      "kind": "function",
      "language": "cpp",
      "location": {
        "bodyEnd": 187,
        "bodyFile": "batteries/buffer.hpp",
        "bodyStart": 184,
        "column": 11,
        "file": "batteries/buffer.hpp",
        "line": 184
      },
      "name": "size",
      "override": false,
      "params": [],
      "pureVirtual": false,
      "refid": "classbatt_1_1ManagedBuffer_1a2e06aa3f55f760b4ec8c1c77d947d7c1",
      "static": false,
      "strong": false,
      "title": "size",
      "type": "usize",
      "typePlain": "usize",
      "url": "/_autogen/Classes/classbatt_1_1ManagedBuffer/#function-size",
      "virtual": false,
      "visibility": "public"
    }
  ],
  "refid": "classbatt_1_1ManagedBuffer",
  "static": false,
  "strong": false,
  "title": "batt::ManagedBuffer",
  "url": "/_autogen/Classes/classbatt_1_1ManagedBuffer/",
  "visibility": "public"
}