{
  "abstract": false,
  "anchor": "",
  "baseClasses": [
    {
      "external": true,
      "name": "T",
      "refid": null,
      "virtual": "non-virtual",
      "visibility": "public"
    }
  ],
  "brief": "Helper template; allows duplicate types to co-exist in the same CompressedTuple. ",
  "category": "classes",
  "const": false,
  "definition": "",
  "details": "The `I` (index) parameter resolves any ambiguity. ",
  "explicit": false,
  "fullname": "batt::CompressedTupleElement",
  "hasAdditionalMembers": false,
  "hasDetails": true,
  "includes": "<batteries/compressed_tuple.hpp>",
  "inline": false,
  "kind": "struct",
  "language": "cpp",
  "location": {
    "bodyEnd": 39,
    "bodyFile": "batteries/compressed_tuple.hpp",
    "bodyStart": 37,
    "column": 1,
    "file": "batteries/compressed_tuple.hpp",
    "line": 37
  },
  "name": "batt::CompressedTupleElement",
  "override": false,
  "parent": {
    "anchor": "",
    "category": "namespaces",
    "fullname": "batt",
    "kind": "namespace",
    "language": "cpp",
    "name": "batt",
    "refid": "namespacebatt",
    "title": "batt",
    "url": "/_autogen/Namespaces/namespacebatt/",
    "visibility": "public"
  },
  "parentBreadcrumbs": [
    {
      "anchor": "",
      "category": "namespaces",
      "fullname": "batt",
      "kind": "namespace",
      "language": "cpp",
      "name": "batt",
      "refid": "namespacebatt",
      "title": "batt",
      "url": "/_autogen/Namespaces/namespacebatt/",
      "visibility": "public"
    }
  ],
  "publicTypes": [
    {
      "abstract": false,
      "anchor": "#using-value-type",
      "category": "types",
      "const": false,
      "definition": "using batt::CompressedTupleElement< I, T >::value_type =  T",
      "explicit": false,
      "fullname": "batt::CompressedTupleElement::value_type",
      "hasDetails": false,
      "inline": false,
      "kind": "using",
      "language": "cpp",
      "location": {
        "bodyFile": "batteries/compressed_tuple.hpp",
        "bodyStart": 38,
        "column": 5,
        "file": "batteries/compressed_tuple.hpp",
        "line": 38
      },
      "name": "value_type",
      "override": false,
      "refid": "structbatt_1_1CompressedTupleElement_1a74e2152355e9d268efb6e10599c8f26b",
      "static": false,
      "strong": false,
      "title": "value_type",
      "type": "T",
      "typePlain": "T",
      "url": "/_autogen/Classes/structbatt_1_1CompressedTupleElement/#using-value-type",
      "visibility": "public"
    }
  ],
  "refid": "structbatt_1_1CompressedTupleElement",
  "static": false,
  "strong": false,
  "summary": "Helper template; allows duplicate types to co-exist in the same CompressedTuple. ",
  "templateParams": [
    {
      "name": "I",
      "type": "usize",
      "typePlain": "usize"
    },
    {
      "name": "",
      "type": "typename T",
      "typePlain": "typename T"
    }
  ],
  "title": "batt::CompressedTupleElement",
  "url": "/_autogen/Classes/structbatt_1_1CompressedTupleElement/",
  "visibility": "public"
}